formattimediff/__init__.py
formattimediff/formattimediff.py
formattimediff-0.2.7.dist-info/LICENSE.txt
formattimediff-0.2.7.dist-info/METADATA
formattimediff-0.2.7.dist-info/WHEEL
formattimediff-0.2.7.dist-info/top_level.txt
formattimediff-0.2.7.dist-info/RECORD
