Metadata-Version: 2.1
Name: formattimediff
Version: 0.2.7
Summary: Simple quick formatting of time differences
Home-page: https://github.com/Datascripter/FormatTimeDiff
Author: Datascripter
Author-email: cody@datascripter.com
Classifier: Programming Language :: Python :: 3
Classifier: License :: OSI Approved :: MIT License
Classifier: Operating System :: OS Independent
Requires-Python: >=3.3
License-File: LICENSE.txt
Requires-Dist: datetime
